README.txt
setup.py
docs/HISTORY.txt
docs/INSTALL.txt
docs/LICENSE.GPL
docs/LICENSE.txt
mailtoplone/__init__.py
mailtoplone.contentrules.egg-info/PKG-INFO
mailtoplone.contentrules.egg-info/SOURCES.txt
mailtoplone.contentrules.egg-info/dependency_links.txt
mailtoplone.contentrules.egg-info/entry_points.txt
mailtoplone.contentrules.egg-info/namespace_packages.txt
mailtoplone.contentrules.egg-info/not-zip-safe
mailtoplone.contentrules.egg-info/requires.txt
mailtoplone.contentrules.egg-info/top_level.txt
mailtoplone/contentrules/CHANGELOG
mailtoplone/contentrules/README.rst
mailtoplone/contentrules/TODO.rst
mailtoplone/contentrules/__init__.py
mailtoplone/contentrules/config.py
mailtoplone/contentrules/configure.zcml
mailtoplone/contentrules/version.txt
mailtoplone/contentrules/actions/__init__.py
mailtoplone/contentrules/actions/configure.zcml
mailtoplone/contentrules/actions/deliver.py
mailtoplone/contentrules/browser/__init__.py
mailtoplone/contentrules/browser/configure.zcml
mailtoplone/contentrules/conditions/__init__.py
mailtoplone/contentrules/conditions/configure.zcml
mailtoplone/contentrules/conditions/emailheader.py
mailtoplone/contentrules/conditions/haspartoftype.py
mailtoplone/contentrules/conditions/sizeofmail.py
mailtoplone/contentrules/tests/__init__.py
mailtoplone/contentrules/tests/base.py
mailtoplone/contentrules/tests/test_doctests.py
mailtoplone/contentrules/tests/test_setup.py