Metadata-Version: 1.0
Name: mailtoplone.contentrules
Version: 0.2.1
Summary: contentrules for mailtoplone
Home-page: https://svn.plone.org/svn/collective/mailtoplone/mailtoplone.contentrules
Author: Hans-Peter Locher
Author-email: hans-peter.locher@inquant.de
License: GPL
Platform: UNKNOWN
Classifier: Framework :: Plone
Classifier: Framework :: Zope2
Classifier: Framework :: Zope3
Classifier: Programming Language :: Python
Classifier: Topic :: Software Development :: Libraries :: Python Modules
